odoo/addons/shopinvader_api_payment/README.rst
odoo/addons/shopinvader_api_payment/__init__.py
odoo/addons/shopinvader_api_payment/__manifest__.py
odoo/addons/shopinvader_api_payment/i18n/shopinvader_api_payment.pot
odoo/addons/shopinvader_api_payment/models/__init__.py
odoo/addons/shopinvader_api_payment/models/payment_transaction.py
odoo/addons/shopinvader_api_payment/readme/CONTRIBUTORS.rst
odoo/addons/shopinvader_api_payment/readme/DESCRIPTION.rst
odoo/addons/shopinvader_api_payment/readme/USAGE.rst
odoo/addons/shopinvader_api_payment/routers/__init__.py
odoo/addons/shopinvader_api_payment/routers/payment.py
odoo/addons/shopinvader_api_payment/routers/utils.py
odoo/addons/shopinvader_api_payment/schemas/__init__.py
odoo/addons/shopinvader_api_payment/schemas/payment_data.py
odoo/addons/shopinvader_api_payment/schemas/payment_icon.py
odoo/addons/shopinvader_api_payment/schemas/payment_provider.py
odoo/addons/shopinvader_api_payment/schemas/transaction_create.py
odoo/addons/shopinvader_api_payment/schemas/transaction_processing_values.py
odoo/addons/shopinvader_api_payment/static/description/index.html
odoo/addons/shopinvader_api_payment/tests/__init__.py
odoo/addons/shopinvader_api_payment/tests/common.py
odoo/addons/shopinvader_api_payment/tests/models.py
odoo/addons/shopinvader_api_payment/tests/test_payable.py
odoo/addons/shopinvader_api_payment/tests/test_payment_router.py
odoo_addon_shopinvader_api_payment-16.0.1.1.0.dist-info/METADATA
odoo_addon_shopinvader_api_payment-16.0.1.1.0.dist-info/WHEEL
odoo_addon_shopinvader_api_payment-16.0.1.1.0.dist-info/top_level.txt
odoo_addon_shopinvader_api_payment-16.0.1.1.0.dist-info/RECORD
