Metadata-Version: 2.1
Name: odoo-addon-shopinvader_api_payment
Version: 16.0.1.1.0
Summary: Shopinvader services to be able to pay (invoices, carts,...)
Home-page: https://github.com/shopinvader/odoo-shopinvader-payment
Author: ACSONE SA/NV,Shopinvader
License: AGPL-3
Classifier: Programming Language :: Python
Classifier: Framework :: Odoo
Classifier: Framework :: Odoo :: 16.0
Classifier: License :: OSI Approved :: GNU Affero General Public License v3
Requires-Python: >=3.10
Requires-Dist: extendable-pydantic >=1.2.0
Requires-Dist: fastapi
Requires-Dist: odoo-addon-extendable <16.1dev,>=16.0dev
Requires-Dist: odoo-addon-extendable-fastapi <16.1dev,>=16.0dev
Requires-Dist: odoo-addon-fastapi <16.1dev,>=16.0dev
Requires-Dist: odoo-addon-pydantic <16.1dev,>=16.0dev
Requires-Dist: odoo <16.1dev,>=16.0a
Requires-Dist: pydantic >=2.0.0
Requires-Dist: pyjwt
